odoo/addons/hr_timesheet_task_domain/README.rst
odoo/addons/hr_timesheet_task_domain/__init__.py
odoo/addons/hr_timesheet_task_domain/__manifest__.py
odoo/addons/hr_timesheet_task_domain/i18n/de.po
odoo/addons/hr_timesheet_task_domain/i18n/es.po
odoo/addons/hr_timesheet_task_domain/i18n/fr.po
odoo/addons/hr_timesheet_task_domain/i18n/hr_timesheet_task_domain.pot
odoo/addons/hr_timesheet_task_domain/i18n/it.po
odoo/addons/hr_timesheet_task_domain/i18n/pt_BR.po
odoo/addons/hr_timesheet_task_domain/models/__init__.py
odoo/addons/hr_timesheet_task_domain/models/account_analytic_line.py
odoo/addons/hr_timesheet_task_domain/readme/CONTRIBUTORS.rst
odoo/addons/hr_timesheet_task_domain/readme/DESCRIPTION.rst
odoo/addons/hr_timesheet_task_domain/static/description/icon.png
odoo/addons/hr_timesheet_task_domain/static/description/index.html
odoo/addons/hr_timesheet_task_domain/tests/__init__.py
odoo/addons/hr_timesheet_task_domain/tests/test_hr_timesheet_task_domain.py
odoo14_addon_hr_timesheet_task_domain-14.0.1.0.1.dev10.dist-info/METADATA
odoo14_addon_hr_timesheet_task_domain-14.0.1.0.1.dev10.dist-info/WHEEL
odoo14_addon_hr_timesheet_task_domain-14.0.1.0.1.dev10.dist-info/top_level.txt
odoo14_addon_hr_timesheet_task_domain-14.0.1.0.1.dev10.dist-info/RECORD
